Metadata-Version: 2.1
Name: grinmw
Version: 0.1.1
Summary: Python wrappers around the Grin wallet V3 and Grin node V2 APIs
Home-page: https://github.com/grinfans/grinmw.py
Author: xiaojay, Blade M. Doyle, marekyggdrasil
Author-email: xiaojay@gmail.com, bladedoyle@gmail.com, marek.yggdrasil@gmail.com
License: MIT
Download-URL: https://github.com/grinfans/grinmw.py/archive/refs/tags/v0.1.1.tar.gz
Platform: UNKNOWN
Classifier: Programming Language :: Python :: 3
Classifier: Programming Language :: Python :: 2
Classifier: License :: OSI Approved :: MIT License
Classifier: Operating System :: OS Independent
